README.rst
setup.py
google_shopping/__init__.py
google_shopping/account_shipping.py
google_shopping/merchant.py
google_shopping/mixins.py
google_shopping/oauth.py
google_shopping/product_statuses.py
google_shopping/products.py
google_shopping/utils.py
python_google_shopping.egg-info/PKG-INFO
python_google_shopping.egg-info/SOURCES.txt
python_google_shopping.egg-info/dependency_links.txt
python_google_shopping.egg-info/requires.txt
python_google_shopping.egg-info/top_level.txt