Metadata-Version: 1.0
Name: python-google-shopping
Version: 0.1
Summary: Python client for Google Shopping API
Home-page: http://blog.namis.me
Author: Nam Ngo
Author-email: nam@kogan.com.au
License: Copyright (c) 2015 Nam Ngo.
